data/handledata.py
101703311_Missing_Data-1.0.1.dist-info/LICENSE.txt
101703311_Missing_Data-1.0.1.dist-info/METADATA
101703311_Missing_Data-1.0.1.dist-info/WHEEL
101703311_Missing_Data-1.0.1.dist-info/entry_points.txt
101703311_Missing_Data-1.0.1.dist-info/top_level.txt
101703311_Missing_Data-1.0.1.dist-info/RECORD
