Metadata-Version: 2.1
Name: 101703311-Missing-Data
Version: 1.0.1
Summary: A python package for handling the missing data from the dataset
Home-page: UNKNOWN
Author: Lokesh Arora
Author-email: 3lokesharora@gmail.com 
License: UNKNOWN
Platform: UNKNOWN
Classifier: Programming Language :: Python :: 3
Classifier: License :: OSI Approved :: MIT License
Classifier: Operating System :: OS Independent
Requires-Python: >=3.6
Requires-Dist: requests
